{
  "VSA No Supply": {
    "signalsEmitted": 26,
    "lastEmitted": "2026-06-04T23:44:17.180Z"
  },
  "Golden Whale Hunter": {
    "signalsEmitted": 1,
    "lastEmitted": "2026-06-04T23:02:52.300Z"
  },
  "Shark Hunt XAU": {
    "signalsEmitted": 43,
    "lastEmitted": "2026-06-04T23:44:17.108Z"
  },
  "Alpha Confluence": {
    "signalsEmitted": 34,
    "lastEmitted": "2026-06-04T23:44:17.109Z"
  },
  "VSA No Demand": {
    "signalsEmitted": 18,
    "lastEmitted": "2026-06-04T23:44:17.106Z"
  },
  "VSA Upthrust": {
    "signalsEmitted": 8,
    "lastEmitted": "2026-06-04T23:41:11.198Z"
  },
  "Squeeze Breakout": {
    "signalsEmitted": 12,
    "lastEmitted": "2026-06-04T23:03:24.454Z"
  },
  "Smart Momentum": {
    "signalsEmitted": 2,
    "lastEmitted": "2026-06-04T23:03:23.077Z"
  },
  "Crypto Whale Hunt": {
    "signalsEmitted": 11,
    "lastEmitted": "2026-06-04T23:03:25.184Z"
  },
  "Alpha Nakamoto": {
    "signalsEmitted": 1,
    "lastEmitted": "2026-06-04T23:03:23.067Z"
  },
  "Alpha Shark": {
    "signalsEmitted": 10,
    "lastEmitted": "2026-06-04T23:03:24.453Z"
  },
  "Ethereum Core": {
    "signalsEmitted": 1,
    "lastEmitted": "2026-06-04T23:03:23.075Z"
  },
  "Alpha Scalper Grid": {
    "signalsEmitted": 2,
    "lastEmitted": "2026-06-04T23:03:23.095Z"
  },
  "Golden Rejection": {
    "signalsEmitted": 1,
    "lastEmitted": "2026-06-04T23:03:24.394Z"
  },
  "Altcoin Sniper": {
    "signalsEmitted": 9,
    "lastEmitted": "2026-06-04T23:03:25.185Z"
  },
  "VSA Shakeout": {
    "signalsEmitted": 3,
    "lastEmitted": "2026-06-04T23:44:08.291Z"
  }
}